<ns1:QueryRequest xmlns:ns1="http://gov.nih.nci.cagrid.data/DataService"> 
      <ns1:cqlQuery> 
           <ns2:CQLQuery xmlns:ns2="http://CQL.caBIG/1/gov.nih.nci.cagrid.CQLQuery" xmlns:xsi="http://www.w3.org/2001/XMLSchema-instance" xsi:schemaLocation="http://CQL.caBIG/1/gov.nih.nci.cagrid.CQLQuery 
 http://cagrid-portal.nci.nih.gov:8080/wsrf/share/schema/CaArraySvc/xsd/Data/1_gov.nih.nci.cagrid.CQLQuery.xsd"> 
                <ns2:Target name="gov.nih.nci.mageom.domain.BioAssayData.MeasuredBioAssayData"> 
                     <ns2:Association name="gov.nih.nci.mageom.domain.Experiment.Experiment"> 
                          <ns2:Attribute name="identifier" value="gov.nih.nci.ncicb.caarray:Experiment:1015897523096000:1" predicate="EQUAL_TO"/> 
                     </ns2:Association> 
                </ns2:Target> 
           </ns2:CQLQuery> 
      </ns1:cqlQuery> 
 </ns1:QueryRequest> 
